taphealth_kafka/__init__.py
taphealth_kafka/client.py
taphealth_kafka/consumer.py
taphealth_kafka/producer.py
taphealth_kafka/topics.py
taphealth_kafka-0.1.6.dist-info/METADATA
taphealth_kafka-0.1.6.dist-info/WHEEL
taphealth_kafka-0.1.6.dist-info/top_level.txt
taphealth_kafka-0.1.6.dist-info/RECORD
