Metadata-Version: 2.4
Name: taphealth-kafka
Version: 0.1.6
Summary: Kafka utilities for TapHealth Python services
Author-email: Afif <afif@tap.health>
License: MIT
Project-URL: Homepage, https://github.com/taphealth/kafka-py
Project-URL: Repository, https://github.com/taphealth/kafka-py
Keywords: kafka,taphealth
Classifier: Development Status :: 4 - Beta
Classifier: Intended Audience :: Developers
Classifier: License :: OSI Approved :: MIT License
Classifier: Operating System :: OS Independent
Classifier: Programming Language :: Python :: 3
Classifier: Programming Language :: Python :: 3.8
Classifier: Programming Language :: Python :: 3.9
Classifier: Programming Language :: Python :: 3.10
Classifier: Programming Language :: Python :: 3.11
Classifier: Programming Language :: Python :: 3.12
Classifier: Programming Language :: Python :: 3.13
Classifier: Topic :: Software Development :: Libraries :: Python Modules
Requires-Python: >=3.8
Requires-Dist: confluent-kafka>=2.0.0
Provides-Extra: dev
Requires-Dist: pre-commit>=3.0.0; extra == "dev"
Requires-Dist: pytest>=7.0.0; extra == "dev"
Requires-Dist: ruff>=0.4.0; extra == "dev"
